DESCRIPTION.rst
MANIFEST.in
setup.py
hcilib/__init__.py
hcilib/__main__.py
hcilib/base/__init__.py
hcilib/base/exceptions.py
hcilib/base/tools.py
hcilib/collect/__init__.py
hcilib/collect/hcidetails.py
hcilib/db/__init__.py
hcilib/loghandler/__init__.py
hcilib/version/__init__.py
hcilib/ziphandler/__init__.py
hcisle.egg-info/PKG-INFO
hcisle.egg-info/SOURCES.txt
hcisle.egg-info/dependency_links.txt
hcisle.egg-info/entry_points.txt
hcisle.egg-info/top_level.txt