Metadata-Version: 2.1
Name: hcisle
Version: 0.1.7
Summary: HCI search log extractor
Home-page: https://hcisle.readthedocs.org
Author: Thorsten Simons
Author-email: sw@snomis.eu
License: MIT
Keywords: Hitachi Content Intelligence
Platform: UNKNOWN
Classifier: Development Status :: 5 - Production/Stable
Classifier: Intended Audience :: System Administrators
Classifier: Topic :: System :: Archiving
Classifier: License :: OSI Approved :: MIT License
Classifier: Programming Language :: Python :: 3
Classifier: Operating System :: OS Independent
Classifier: Natural Language :: English
